{"747abc33-e218-4dfa-97c3-d6b4c251a79a":{"object":"page","id":"747abc33-e218-4dfa-97c3-d6b4c251a79a","created_time":"2021-11-18T02:09:00.000Z","last_edited_time":"2021-11-18T02:10:00.000Z","cover":null,"icon":null,"parent":{"type":"database_id","database_id":"ec103091-0718-41d6-b50a-3b378370428b"},"archived":false,"properties":{"Tags":{"id":"RVSR","type":"multi_select","multi_select":[]},"slug":{"id":"v%60jt","type":"rich_text","rich_text":[]},"Name":{"id":"title","type":"title","title":[{"type":"text","text":{"content":"Second Post","link":null},"annotations":{"bold":false,"italic":false,"strikethrough":false,"underline":false,"code":false,"color":"default"},"plain_text":"Second Post","href":null}]}},"url":"https://www.notion.so/Second-Post-747abc33e2184dfa97c3d6b4c251a79a","blocks":[],"local":{},"slug":""},"db8c86c9-0240-4bd5-99cc-9e98b3a9a19e":{"object":"page","id":"db8c86c9-0240-4bd5-99cc-9e98b3a9a19e","created_time":"2021-11-13T22:20:00.000Z","last_edited_time":"2021-11-20T20:51:00.000Z","cover":{"type":"file","file":{"url":"https://s3.us-west-2.amazonaws.com/secure.notion-static.com/7e6128eb-fc69-4688-8b4e-a60c3c5e44ec/Frame_1.svg?X-Amz-Algorithm=AWS4-HMAC-SHA256&X-Amz-Content-Sha256=UNSIGNED-PAYLOAD&X-Amz-Credential=AKIAT73L2G45EIPT3X45%2F20211120%2Fus-west-2%2Fs3%2Faws4_request&X-Amz-Date=20211120T205419Z&X-Amz-Expires=3600&X-Amz-Signature=7339b487f6978cfaf4fec53b8a01b71eb5353a2f7ec85cda476f5b46bae248bd&X-Amz-SignedHeaders=host&x-id=GetObject","expiry_time":"2021-11-20T21:54:19.687Z"}},"icon":null,"parent":{"type":"database_id","database_id":"ec103091-0718-41d6-b50a-3b378370428b"},"archived":false,"properties":{"Tags":{"id":"RVSR","type":"multi_select","multi_select":[{"id":"bdb522ee-3714-4bd3-85fc-c4d494c4dda7","name":"Test","color":"yellow"},{"id":"d49d7a96-38e9-4c9e-a4eb-5a81ca48868b","name":"Research","color":"default"}]},"slug":{"id":"v%60jt","type":"rich_text","rich_text":[{"type":"text","text":{"content":"test","link":null},"annotations":{"bold":false,"italic":false,"strikethrough":false,"underline":false,"code":false,"color":"default"},"plain_text":"test","href":null}]},"Name":{"id":"title","type":"title","title":[{"type":"text","text":{"content":"First Post","link":null},"annotations":{"bold":false,"italic":false,"strikethrough":false,"underline":false,"code":false,"color":"default"},"plain_text":"First Post","href":null}]}},"url":"https://www.notion.so/First-Post-db8c86c902404bd599cc9e98b3a9a19e","blocks":[{"object":"block","id":"b77bb3a2-4500-4590-aeb5-a01b32e3dd3d","created_time":"2021-11-13T22:20:00.000Z","last_edited_time":"2021-11-13T22:20:00.000Z","has_children":false,"archived":false,"type":"paragraph","paragraph":{"text":[{"type":"text","text":{"content":"Lorem ipsum dolor sit amet, consectetuer adipiscing elit. Aenean commodo ligula","link":null},"annotations":{"bold":false,"italic":false,"strikethrough":false,"underline":false,"code":false,"color":"default"},"plain_text":"Lorem ipsum dolor sit amet, consectetuer adipiscing elit. Aenean commodo ligula","href":null}]}},{"object":"block","id":"40cb5253-42b6-4feb-ba55-b05610c2e09c","created_time":"2021-11-13T22:20:00.000Z","last_edited_time":"2021-11-13T22:21:00.000Z","has_children":false,"archived":false,"type":"paragraph","paragraph":{"text":[{"type":"text","text":{"content":"Bolded","link":null},"annotations":{"bold":true,"italic":false,"strikethrough":false,"underline":false,"code":false,"color":"default"},"plain_text":"Bolded","href":null},{"type":"text","text":{"content":" text ","link":null},"annotations":{"bold":false,"italic":false,"strikethrough":false,"underline":false,"code":false,"color":"default"},"plain_text":" text ","href":null}]}},{"object":"block","id":"609c6a17-07f6-4bbe-9a14-6928b6317ff4","created_time":"2021-11-13T22:21:00.000Z","last_edited_time":"2021-11-13T22:21:00.000Z","has_children":false,"archived":false,"type":"paragraph","paragraph":{"text":[{"type":"text","text":{"content":"Italics","link":null},"annotations":{"bold":false,"italic":true,"strikethrough":false,"underline":false,"code":false,"color":"default"},"plain_text":"Italics","href":null},{"type":"text","text":{"content":" text","link":null},"annotations":{"bold":false,"italic":false,"strikethrough":false,"underline":false,"code":false,"color":"default"},"plain_text":" text","href":null}]}},{"object":"block","id":"e362c59b-4399-47cb-9b5d-932af02d0025","created_time":"2021-11-13T22:21:00.000Z","last_edited_time":"2021-11-13T22:46:00.000Z","has_children":false,"archived":false,"type":"paragraph","paragraph":{"text":[{"type":"text","text":{"content":"Underline","link":null},"annotations":{"bold":false,"italic":false,"strikethrough":false,"underline":true,"code":false,"color":"default"},"plain_text":"Underline","href":null},{"type":"text","text":{"content":"d","link":null},"annotations":{"bold":true,"italic":true,"strikethrough":true,"underline":true,"code":false,"color":"default"},"plain_text":"d","href":null},{"type":"text","text":{"content":" text","link":null},"annotations":{"bold":true,"italic":true,"strikethrough":true,"underline":false,"code":false,"color":"default"},"plain_text":" text","href":null}]}},{"object":"block","id":"1aa5bbcf-8b46-4ddd-8030-cacdf99576bf","created_time":"2021-11-13T22:21:00.000Z","last_edited_time":"2021-11-13T22:21:00.000Z","has_children":false,"archived":false,"type":"paragraph","paragraph":{"text":[{"type":"text","text":{"content":"Striked","link":null},"annotations":{"bold":false,"italic":false,"strikethrough":true,"underline":false,"code":false,"color":"default"},"plain_text":"Striked","href":null},{"type":"text","text":{"content":" out text","link":null},"annotations":{"bold":false,"italic":false,"strikethrough":false,"underline":false,"code":false,"color":"default"},"plain_text":" out text","href":null}]}},{"object":"block","id":"bfff6504-d1fd-4e7f-b224-2b48e92c76ce","created_time":"2021-11-13T22:20:00.000Z","last_edited_time":"2021-11-13T22:21:00.000Z","has_children":false,"archived":false,"type":"paragraph","paragraph":{"text":[{"type":"text","text":{"content":"Here is ","link":null},"annotations":{"bold":false,"italic":false,"strikethrough":false,"underline":false,"code":false,"color":"default"},"plain_text":"Here is ","href":null},{"type":"text","text":{"content":"some code","link":null},"annotations":{"bold":false,"italic":false,"strikethrough":false,"underline":false,"code":true,"color":"default"},"plain_text":"some code","href":null}]}},{"object":"block","id":"575686dc-be75-4063-ae27-f28ecf1033b0","created_time":"2021-11-13T22:21:00.000Z","last_edited_time":"2021-11-13T22:22:00.000Z","has_children":false,"archived":false,"type":"paragraph","paragraph":{"text":[{"type":"equation","equation":{"expression":"y = mx + b"},"annotations":{"bold":false,"italic":false,"strikethrough":false,"underline":false,"code":false,"color":"default"},"plain_text":"y = mx + b","href":null}]}},{"object":"block","id":"69065f4e-9b49-4ce7-8b47-fc7af4efd4bf","created_time":"2021-11-13T22:22:00.000Z","last_edited_time":"2021-11-13T22:45:00.000Z","has_children":false,"archived":false,"type":"paragraph","paragraph":{"text":[{"type":"text","text":{"content":"Today I had asdkjfksjdfkj","link":null},"annotations":{"bold":false,"italic":false,"strikethrough":false,"underline":false,"code":false,"color":"default"},"plain_text":"Today I had asdkjfksjdfkj","href":null}]}},{"object":"block","id":"ff50af4e-c15b-4ef5-b9cf-4a5b24a374aa","created_time":"2021-11-13T22:45:00.000Z","last_edited_time":"2021-11-17T00:09:00.000Z","has_children":false,"archived":false,"type":"heading_1","heading_1":{"text":[{"type":"text","text":{"content":"Heading 1 ","link":null},"annotations":{"bold":false,"italic":false,"strikethrough":false,"underline":false,"code":false,"color":"default"},"plain_text":"Heading 1 ","href":null},{"type":"mention","mention":{"type":"user","user":{"object":"user","id":"e59c945c-cc91-4d0e-a6c9-e3646e387b3b","name":"Vincenzo Marconi","avatar_url":null,"type":"person","person":{"email":"vincenzorm117@gmail.com"}}},"annotations":{"bold":false,"italic":false,"strikethrough":false,"underline":false,"code":false,"color":"default"},"plain_text":"@Vincenzo Marconi","href":null},{"type":"text","text":{"content":" ","link":null},"annotations":{"bold":false,"italic":false,"strikethrough":false,"underline":false,"code":false,"color":"default"},"plain_text":" ","href":null}]}},{"object":"block","id":"6429362d-a61c-4b71-aabc-7dd6971bae30","created_time":"2021-11-13T22:45:00.000Z","last_edited_time":"2021-11-17T00:09:00.000Z","has_children":false,"archived":false,"type":"heading_2","heading_2":{"text":[{"type":"text","text":{"content":"Heading 2","link":null},"annotations":{"bold":false,"italic":false,"strikethrough":false,"underline":false,"code":false,"color":"default"},"plain_text":"Heading 2","href":null}]}},{"object":"block","id":"bc4bcffc-ec7b-4ac5-acc5-9a504667b1cd","created_time":"2021-11-17T00:09:00.000Z","last_edited_time":"2021-11-17T00:09:00.000Z","has_children":false,"archived":false,"type":"heading_3","heading_3":{"text":[{"type":"text","text":{"content":"Heading 3","link":null},"annotations":{"bold":false,"italic":false,"strikethrough":false,"underline":false,"code":false,"color":"default"},"plain_text":"Heading 3","href":null}]}},{"object":"block","id":"b000e65f-5a62-46ad-b377-386e6ad89f3a","created_time":"2021-11-17T00:09:00.000Z","last_edited_time":"2021-11-20T17:33:00.000Z","has_children":true,"archived":false,"type":"unsupported","unsupported":{}},{"object":"block","id":"02d1aec5-cfab-4124-b89d-d2ca17a733b2","created_time":"2021-11-19T04:10:00.000Z","last_edited_time":"2021-11-20T17:33:00.000Z","has_children":false,"archived":false,"type":"paragraph","paragraph":{"text":[]}},{"object":"block","id":"aaa11617-35ff-43a6-a21c-18645efa3437","created_time":"2021-11-19T04:10:00.000Z","last_edited_time":"2021-11-20T17:39:00.000Z","has_children":false,"archived":false,"type":"paragraph","paragraph":{"text":[{"type":"text","text":{"content":"Lorem ","link":null},"annotations":{"bold":false,"italic":false,"strikethrough":false,"underline":false,"code":false,"color":"default"},"plain_text":"Lorem ","href":null},{"type":"text","text":{"content":"ipsum","link":null},"annotations":{"bold":false,"italic":false,"strikethrough":false,"underline":false,"code":false,"color":"gray"},"plain_text":"ipsum","href":null},{"type":"text","text":{"content":" ","link":null},"annotations":{"bold":false,"italic":false,"strikethrough":false,"underline":false,"code":false,"color":"default"},"plain_text":" ","href":null},{"type":"text","text":{"content":"dolor","link":null},"annotations":{"bold":false,"italic":false,"strikethrough":false,"underline":false,"code":false,"color":"brown"},"plain_text":"dolor","href":null},{"type":"text","text":{"content":" ","link":null},"annotations":{"bold":false,"italic":false,"strikethrough":false,"underline":false,"code":false,"color":"default"},"plain_text":" ","href":null},{"type":"text","text":{"content":"sit","link":null},"annotations":{"bold":false,"italic":false,"strikethrough":false,"underline":false,"code":false,"color":"orange"},"plain_text":"sit","href":null},{"type":"text","text":{"content":" ","link":null},"annotations":{"bold":false,"italic":false,"strikethrough":false,"underline":false,"code":false,"color":"default"},"plain_text":" ","href":null},{"type":"text","text":{"content":"amet","link":null},"annotations":{"bold":false,"italic":false,"strikethrough":false,"underline":false,"code":false,"color":"yellow"},"plain_text":"amet","href":null},{"type":"text","text":{"content":", ","link":null},"annotations":{"bold":false,"italic":false,"strikethrough":false,"underline":false,"code":false,"color":"default"},"plain_text":", ","href":null},{"type":"text","text":{"content":"consectetuer","link":null},"annotations":{"bold":false,"italic":false,"strikethrough":false,"underline":false,"code":false,"color":"green"},"plain_text":"consectetuer","href":null},{"type":"text","text":{"content":" ","link":null},"annotations":{"bold":false,"italic":false,"strikethrough":false,"underline":false,"code":false,"color":"default"},"plain_text":" ","href":null},{"type":"text","text":{"content":"adipiscing","link":null},"annotations":{"bold":false,"italic":false,"strikethrough":false,"underline":false,"code":false,"color":"blue"},"plain_text":"adipiscing","href":null},{"type":"text","text":{"content":" ","link":null},"annotations":{"bold":false,"italic":false,"strikethrough":false,"underline":false,"code":false,"color":"default"},"plain_text":" ","href":null},{"type":"text","text":{"content":"elit","link":null},"annotations":{"bold":false,"italic":false,"strikethrough":false,"underline":false,"code":false,"color":"purple"},"plain_text":"elit","href":null},{"type":"text","text":{"content":". ","link":null},"annotations":{"bold":false,"italic":false,"strikethrough":false,"underline":false,"code":false,"color":"default"},"plain_text":". ","href":null},{"type":"text","text":{"content":"Aenean","link":null},"annotations":{"bold":false,"italic":false,"strikethrough":false,"underline":false,"code":false,"color":"pink"},"plain_text":"Aenean","href":null},{"type":"text","text":{"content":" ","link":null},"annotations":{"bold":false,"italic":false,"strikethrough":false,"underline":false,"code":false,"color":"default"},"plain_text":" ","href":null},{"type":"text","text":{"content":"commodo","link":null},"annotations":{"bold":false,"italic":false,"strikethrough":false,"underline":false,"code":false,"color":"red"},"plain_text":"commodo","href":null},{"type":"text","text":{"content":" ligula\neget ","link":null},"annotations":{"bold":false,"italic":false,"strikethrough":false,"underline":false,"code":false,"color":"default"},"plain_text":" ligula\neget ","href":null},{"type":"text","text":{"content":"dolor","link":null},"annotations":{"bold":false,"italic":false,"strikethrough":false,"underline":false,"code":false,"color":"gray_background"},"plain_text":"dolor","href":null},{"type":"text","text":{"content":". ","link":null},"annotations":{"bold":false,"italic":false,"strikethrough":false,"underline":false,"code":false,"color":"default"},"plain_text":". ","href":null},{"type":"text","text":{"content":"Aenean","link":null},"annotations":{"bold":false,"italic":false,"strikethrough":false,"underline":false,"code":false,"color":"brown_background"},"plain_text":"Aenean","href":null},{"type":"text","text":{"content":" ","link":null},"annotations":{"bold":false,"italic":false,"strikethrough":false,"underline":false,"code":false,"color":"default"},"plain_text":" ","href":null},{"type":"text","text":{"content":"massa","link":null},"annotations":{"bold":false,"italic":false,"strikethrough":false,"underline":false,"code":false,"color":"orange_background"},"plain_text":"massa","href":null},{"type":"text","text":{"content":". ","link":null},"annotations":{"bold":false,"italic":false,"strikethrough":false,"underline":false,"code":false,"color":"default"},"plain_text":". ","href":null},{"type":"text","text":{"content":"Cum","link":null},"annotations":{"bold":false,"italic":false,"strikethrough":false,"underline":false,"code":false,"color":"yellow_background"},"plain_text":"Cum","href":null},{"type":"text","text":{"content":" ","link":null},"annotations":{"bold":false,"italic":false,"strikethrough":false,"underline":false,"code":false,"color":"default"},"plain_text":" ","href":null},{"type":"text","text":{"content":"sociis","link":null},"annotations":{"bold":false,"italic":false,"strikethrough":false,"underline":false,"code":false,"color":"green_background"},"plain_text":"sociis","href":null},{"type":"text","text":{"content":" ","link":null},"annotations":{"bold":false,"italic":false,"strikethrough":false,"underline":false,"code":false,"color":"default"},"plain_text":" ","href":null},{"type":"text","text":{"content":"natoque","link":null},"annotations":{"bold":false,"italic":false,"strikethrough":false,"underline":false,"code":false,"color":"blue_background"},"plain_text":"natoque","href":null},{"type":"text","text":{"content":" ","link":null},"annotations":{"bold":false,"italic":false,"strikethrough":false,"underline":false,"code":false,"color":"default"},"plain_text":" ","href":null},{"type":"text","text":{"content":"penatibus","link":null},"annotations":{"bold":false,"italic":false,"strikethrough":false,"underline":false,"code":false,"color":"purple_background"},"plain_text":"penatibus","href":null},{"type":"text","text":{"content":" ","link":null},"annotations":{"bold":false,"italic":false,"strikethrough":false,"underline":false,"code":false,"color":"default"},"plain_text":" ","href":null},{"type":"text","text":{"content":"et","link":null},"annotations":{"bold":false,"italic":false,"strikethrough":false,"underline":false,"code":false,"color":"pink_background"},"plain_text":"et","href":null},{"type":"text","text":{"content":" ","link":null},"annotations":{"bold":false,"italic":false,"strikethrough":false,"underline":false,"code":false,"color":"default"},"plain_text":" ","href":null},{"type":"text","text":{"content":"magnis","link":null},"annotations":{"bold":false,"italic":false,"strikethrough":false,"underline":false,"code":false,"color":"red_background"},"plain_text":"magnis","href":null},{"type":"text","text":{"content":" dis parturient\nmontes, ","link":null},"annotations":{"bold":false,"italic":false,"strikethrough":false,"underline":false,"code":false,"color":"default"},"plain_text":" dis parturient\nmontes, ","href":null},{"type":"text","text":{"content":"nascetur","link":null},"annotations":{"bold":false,"italic":false,"strikethrough":false,"underline":false,"code":false,"color":"gray_background"},"plain_text":"nascetur","href":null},{"type":"text","text":{"content":" ridiculus mus. Donec quam felis, ultricies nec, pellentesque\neu, pretium quis, sem. Nulla consequat massa quis enim. Donec pede justo,\nfringilla vel, aliquet nec, vulputate eget, arcu. In enim justo, rhoncus ut,\nimperdiet a, venenatis vitae, justo. Nullam dictum felis eu pede mollis pretium.\nInteger tincidunt. Cras dapibus. Vivamus elementum semper nisi. Aenean vulputate\neleifend tellus. Aenean leo ligula, porttitor eu, consequat vitae, eleifend ac,\nenim. Aliquam lorem ante, dapibus in, viverra quis, feugiat a, tellus. Phasellus\nviverra nulla ut metus varius laoreet. Quisque rutrum. Aenean imperdiet. Etiam\nultricies nisi vel augue. Curabitur ullamcorper ultricies nisi. Nam eget dui.\nLorem ipsum dolor sit amet, consectetuer adipiscing elit. \nAenean commodo ligula\neget dolor. Aenean massa. Cum sociis natoque penatibus et magnis dis parturient\nmontes, nascetur ridiculus mus. Donec quam felis, ultricies nec, pellentesque\neu, pretium quis, sem. Nulla consequat massa quis enim. Donec pede justo,\nfringilla vel, aliquet nec, vulputate eget, arcu. In enim justo, rhoncus ut,\nimperdiet a, venenatis vitae, justo. Nullam dictum felis eu pede mollis pretium.\nInteger tincidunt. Cras dapibus. Vivamus elementum semper nisi. Aenean vulputate\neleifend tellus. Aenean leo ligula, porttitor eu, consequat vitae, eleifend ac,\nenim. Aliquam lorem ante, dapibus in, viverra quis, feugiat a, tellus. Phasellus","link":null},"annotations":{"bold":false,"italic":false,"strikethrough":false,"underline":false,"code":false,"color":"default"},"plain_text":" ridiculus mus. Donec quam felis, ultricies nec, pellentesque\neu, pretium quis, sem. Nulla consequat massa quis enim. Donec pede justo,\nfringilla vel, aliquet nec, vulputate eget, arcu. In enim justo, rhoncus ut,\nimperdiet a, venenatis vitae, justo. Nullam dictum felis eu pede mollis pretium.\nInteger tincidunt. Cras dapibus. Vivamus elementum semper nisi. Aenean vulputate\neleifend tellus. Aenean leo ligula, porttitor eu, consequat vitae, eleifend ac,\nenim. Aliquam lorem ante, dapibus in, viverra quis, feugiat a, tellus. Phasellus\nviverra nulla ut metus varius laoreet. Quisque rutrum. Aenean imperdiet. Etiam\nultricies nisi vel augue. Curabitur ullamcorper ultricies nisi. Nam eget dui.\nLorem ipsum dolor sit amet, consectetuer adipiscing elit. \nAenean commodo ligula\neget dolor. Aenean massa. Cum sociis natoque penatibus et magnis dis parturient\nmontes, nascetur ridiculus mus. Donec quam felis, ultricies nec, pellentesque\neu, pretium quis, sem. Nulla consequat massa quis enim. Donec pede justo,\nfringilla vel, aliquet nec, vulputate eget, arcu. In enim justo, rhoncus ut,\nimperdiet a, venenatis vitae, justo. Nullam dictum felis eu pede mollis pretium.\nInteger tincidunt. Cras dapibus. Vivamus elementum semper nisi. Aenean vulputate\neleifend tellus. Aenean leo ligula, porttitor eu, consequat vitae, eleifend ac,\nenim. Aliquam lorem ante, dapibus in, viverra quis, feugiat a, tellus. Phasellus","href":null}]}},{"object":"block","id":"fdb5355a-5d60-49dc-97bb-06f3e9f2f330","created_time":"2021-11-20T17:33:00.000Z","last_edited_time":"2021-11-20T18:55:00.000Z","has_children":false,"archived":false,"type":"code","code":{"text":[{"type":"text","text":{"content":"function Hello() {\n\tconsole.log('Hello World! 🚀');\n}\n\nHello()\n// Hello World! 🚀","link":null},"annotations":{"bold":false,"italic":false,"strikethrough":false,"underline":false,"code":false,"color":"default"},"plain_text":"function Hello() {\n\tconsole.log('Hello World! 🚀');\n}\n\nHello()\n// Hello World! 🚀","href":null}],"language":"javascript"}},{"object":"block","type":"bulleted_list","id":"142fd628-6536-4f7f-aea8-a6bd6d951b9e","bulleted_list":[{"object":"block","id":"4d25704e-63b1-4f1b-bfd4-0764186deaaf","created_time":"2021-11-20T19:03:00.000Z","last_edited_time":"2021-11-20T19:03:00.000Z","has_children":false,"archived":false,"type":"bulleted_list_item","bulleted_list_item":{"text":[{"type":"text","text":{"content":"Item one","link":null},"annotations":{"bold":false,"italic":false,"strikethrough":false,"underline":false,"code":false,"color":"default"},"plain_text":"Item one","href":null}]}},{"object":"block","id":"47a1b4ba-ee9d-4996-a4c3-cbd11c67f9dd","created_time":"2021-11-20T19:03:00.000Z","last_edited_time":"2021-11-20T19:03:00.000Z","has_children":false,"archived":false,"type":"bulleted_list_item","bulleted_list_item":{"text":[{"type":"text","text":{"content":"Item two","link":null},"annotations":{"bold":false,"italic":false,"strikethrough":false,"underline":false,"code":false,"color":"default"},"plain_text":"Item two","href":null}]}}]},{"object":"block","type":"numbered_list","id":"5ccae244-628a-4cb5-9feb-2011bde04c4d","numbered_list":[{"object":"block","id":"a7d39d42-255e-44ab-9054-67af10b642b2","created_time":"2021-11-20T19:05:00.000Z","last_edited_time":"2021-11-20T19:05:00.000Z","has_children":false,"archived":false,"type":"numbered_list_item","numbered_list_item":{"text":[{"type":"text","text":{"content":"Item one","link":null},"annotations":{"bold":false,"italic":false,"strikethrough":false,"underline":false,"code":false,"color":"default"},"plain_text":"Item one","href":null}]}},{"object":"block","id":"c818e63b-968d-4d95-b07a-ca1e3c2d24f9","created_time":"2021-11-20T19:05:00.000Z","last_edited_time":"2021-11-20T19:06:00.000Z","has_children":false,"archived":false,"type":"numbered_list_item","numbered_list_item":{"text":[{"type":"text","text":{"content":"Item two","link":null},"annotations":{"bold":false,"italic":false,"strikethrough":false,"underline":false,"code":false,"color":"default"},"plain_text":"Item two","href":null}]}}]},{"object":"block","id":"fbaa68b5-e786-44f5-8fdd-31b59af6c6ae","created_time":"2021-11-20T20:51:00.000Z","last_edited_time":"2021-11-20T20:51:00.000Z","has_children":false,"archived":false,"type":"to_do","to_do":{"text":[{"type":"text","text":{"content":"Item one","link":null},"annotations":{"bold":false,"italic":false,"strikethrough":false,"underline":false,"code":false,"color":"default"},"plain_text":"Item one","href":null}],"checked":false}},{"object":"block","id":"3f5db090-7841-4121-8d3f-ed9cecc3c953","created_time":"2021-11-20T20:51:00.000Z","last_edited_time":"2021-11-20T20:51:00.000Z","has_children":false,"archived":false,"type":"to_do","to_do":{"text":[{"type":"text","text":{"content":"Item two","link":null},"annotations":{"bold":false,"italic":false,"strikethrough":false,"underline":false,"code":false,"color":"default"},"plain_text":"Item two","href":null}],"checked":false}},{"object":"block","id":"1506f17a-6834-4ded-bf6c-746c8f1df30d","created_time":"2021-11-20T20:51:00.000Z","last_edited_time":"2021-11-20T20:51:00.000Z","has_children":false,"archived":false,"type":"to_do","to_do":{"text":[{"type":"text","text":{"content":"Item one","link":null},"annotations":{"bold":false,"italic":false,"strikethrough":false,"underline":false,"code":false,"color":"default"},"plain_text":"Item one","href":null}],"checked":true}},{"object":"block","id":"2bc46609-ec1e-45fa-a3c0-c77f6f33b306","created_time":"2021-11-20T20:51:00.000Z","last_edited_time":"2021-11-20T20:51:00.000Z","has_children":false,"archived":false,"type":"to_do","to_do":{"text":[{"type":"text","text":{"content":"Item two","link":null},"annotations":{"bold":false,"italic":false,"strikethrough":false,"underline":false,"code":false,"color":"default"},"plain_text":"Item two","href":null}],"checked":true}}],"local":{"cover":{"localFileName":"d7256e6c-8ffd-4275-991e-3f3d23a48045.svg","localUrl":"/blog/d7256e6c-8ffd-4275-991e-3f3d23a48045.svg"}},"slug":"test"},"b77bb3a2-4500-4590-aeb5-a01b32e3dd3d":{"object":"block","id":"b77bb3a2-4500-4590-aeb5-a01b32e3dd3d","created_time":"2021-11-13T22:20:00.000Z","last_edited_time":"2021-11-13T22:20:00.000Z","has_children":false,"archived":false,"type":"paragraph","paragraph":{"text":[{"type":"text","text":{"content":"Lorem ipsum dolor sit amet, consectetuer adipiscing elit. Aenean commodo ligula","link":null},"annotations":{"bold":false,"italic":false,"strikethrough":false,"underline":false,"code":false,"color":"default"},"plain_text":"Lorem ipsum dolor sit amet, consectetuer adipiscing elit. Aenean commodo ligula","href":null}]}},"40cb5253-42b6-4feb-ba55-b05610c2e09c":{"object":"block","id":"40cb5253-42b6-4feb-ba55-b05610c2e09c","created_time":"2021-11-13T22:20:00.000Z","last_edited_time":"2021-11-13T22:21:00.000Z","has_children":false,"archived":false,"type":"paragraph","paragraph":{"text":[{"type":"text","text":{"content":"Bolded","link":null},"annotations":{"bold":true,"italic":false,"strikethrough":false,"underline":false,"code":false,"color":"default"},"plain_text":"Bolded","href":null},{"type":"text","text":{"content":" text ","link":null},"annotations":{"bold":false,"italic":false,"strikethrough":false,"underline":false,"code":false,"color":"default"},"plain_text":" text ","href":null}]}},"609c6a17-07f6-4bbe-9a14-6928b6317ff4":{"object":"block","id":"609c6a17-07f6-4bbe-9a14-6928b6317ff4","created_time":"2021-11-13T22:21:00.000Z","last_edited_time":"2021-11-13T22:21:00.000Z","has_children":false,"archived":false,"type":"paragraph","paragraph":{"text":[{"type":"text","text":{"content":"Italics","link":null},"annotations":{"bold":false,"italic":true,"strikethrough":false,"underline":false,"code":false,"color":"default"},"plain_text":"Italics","href":null},{"type":"text","text":{"content":" text","link":null},"annotations":{"bold":false,"italic":false,"strikethrough":false,"underline":false,"code":false,"color":"default"},"plain_text":" text","href":null}]}},"e362c59b-4399-47cb-9b5d-932af02d0025":{"object":"block","id":"e362c59b-4399-47cb-9b5d-932af02d0025","created_time":"2021-11-13T22:21:00.000Z","last_edited_time":"2021-11-13T22:46:00.000Z","has_children":false,"archived":false,"type":"paragraph","paragraph":{"text":[{"type":"text","text":{"content":"Underline","link":null},"annotations":{"bold":false,"italic":false,"strikethrough":false,"underline":true,"code":false,"color":"default"},"plain_text":"Underline","href":null},{"type":"text","text":{"content":"d","link":null},"annotations":{"bold":true,"italic":true,"strikethrough":true,"underline":true,"code":false,"color":"default"},"plain_text":"d","href":null},{"type":"text","text":{"content":" text","link":null},"annotations":{"bold":true,"italic":true,"strikethrough":true,"underline":false,"code":false,"color":"default"},"plain_text":" text","href":null}]}},"1aa5bbcf-8b46-4ddd-8030-cacdf99576bf":{"object":"block","id":"1aa5bbcf-8b46-4ddd-8030-cacdf99576bf","created_time":"2021-11-13T22:21:00.000Z","last_edited_time":"2021-11-13T22:21:00.000Z","has_children":false,"archived":false,"type":"paragraph","paragraph":{"text":[{"type":"text","text":{"content":"Striked","link":null},"annotations":{"bold":false,"italic":false,"strikethrough":true,"underline":false,"code":false,"color":"default"},"plain_text":"Striked","href":null},{"type":"text","text":{"content":" out text","link":null},"annotations":{"bold":false,"italic":false,"strikethrough":false,"underline":false,"code":false,"color":"default"},"plain_text":" out text","href":null}]}},"bfff6504-d1fd-4e7f-b224-2b48e92c76ce":{"object":"block","id":"bfff6504-d1fd-4e7f-b224-2b48e92c76ce","created_time":"2021-11-13T22:20:00.000Z","last_edited_time":"2021-11-13T22:21:00.000Z","has_children":false,"archived":false,"type":"paragraph","paragraph":{"text":[{"type":"text","text":{"content":"Here is ","link":null},"annotations":{"bold":false,"italic":false,"strikethrough":false,"underline":false,"code":false,"color":"default"},"plain_text":"Here is ","href":null},{"type":"text","text":{"content":"some code","link":null},"annotations":{"bold":false,"italic":false,"strikethrough":false,"underline":false,"code":true,"color":"default"},"plain_text":"some code","href":null}]}},"575686dc-be75-4063-ae27-f28ecf1033b0":{"object":"block","id":"575686dc-be75-4063-ae27-f28ecf1033b0","created_time":"2021-11-13T22:21:00.000Z","last_edited_time":"2021-11-13T22:22:00.000Z","has_children":false,"archived":false,"type":"paragraph","paragraph":{"text":[{"type":"equation","equation":{"expression":"y = mx + b"},"annotations":{"bold":false,"italic":false,"strikethrough":false,"underline":false,"code":false,"color":"default"},"plain_text":"y = mx + b","href":null}]}},"69065f4e-9b49-4ce7-8b47-fc7af4efd4bf":{"object":"block","id":"69065f4e-9b49-4ce7-8b47-fc7af4efd4bf","created_time":"2021-11-13T22:22:00.000Z","last_edited_time":"2021-11-13T22:45:00.000Z","has_children":false,"archived":false,"type":"paragraph","paragraph":{"text":[{"type":"text","text":{"content":"Today I had asdkjfksjdfkj","link":null},"annotations":{"bold":false,"italic":false,"strikethrough":false,"underline":false,"code":false,"color":"default"},"plain_text":"Today I had asdkjfksjdfkj","href":null}]}},"ff50af4e-c15b-4ef5-b9cf-4a5b24a374aa":{"object":"block","id":"ff50af4e-c15b-4ef5-b9cf-4a5b24a374aa","created_time":"2021-11-13T22:45:00.000Z","last_edited_time":"2021-11-17T00:09:00.000Z","has_children":false,"archived":false,"type":"heading_1","heading_1":{"text":[{"type":"text","text":{"content":"Heading 1 ","link":null},"annotations":{"bold":false,"italic":false,"strikethrough":false,"underline":false,"code":false,"color":"default"},"plain_text":"Heading 1 ","href":null},{"type":"mention","mention":{"type":"user","user":{"object":"user","id":"e59c945c-cc91-4d0e-a6c9-e3646e387b3b","name":"Vincenzo Marconi","avatar_url":null,"type":"person","person":{"email":"vincenzorm117@gmail.com"}}},"annotations":{"bold":false,"italic":false,"strikethrough":false,"underline":false,"code":false,"color":"default"},"plain_text":"@Vincenzo Marconi","href":null},{"type":"text","text":{"content":" ","link":null},"annotations":{"bold":false,"italic":false,"strikethrough":false,"underline":false,"code":false,"color":"default"},"plain_text":" ","href":null}]}},"6429362d-a61c-4b71-aabc-7dd6971bae30":{"object":"block","id":"6429362d-a61c-4b71-aabc-7dd6971bae30","created_time":"2021-11-13T22:45:00.000Z","last_edited_time":"2021-11-17T00:09:00.000Z","has_children":false,"archived":false,"type":"heading_2","heading_2":{"text":[{"type":"text","text":{"content":"Heading 2","link":null},"annotations":{"bold":false,"italic":false,"strikethrough":false,"underline":false,"code":false,"color":"default"},"plain_text":"Heading 2","href":null}]}},"bc4bcffc-ec7b-4ac5-acc5-9a504667b1cd":{"object":"block","id":"bc4bcffc-ec7b-4ac5-acc5-9a504667b1cd","created_time":"2021-11-17T00:09:00.000Z","last_edited_time":"2021-11-17T00:09:00.000Z","has_children":false,"archived":false,"type":"heading_3","heading_3":{"text":[{"type":"text","text":{"content":"Heading 3","link":null},"annotations":{"bold":false,"italic":false,"strikethrough":false,"underline":false,"code":false,"color":"default"},"plain_text":"Heading 3","href":null}]}},"b000e65f-5a62-46ad-b377-386e6ad89f3a":{"object":"block","id":"b000e65f-5a62-46ad-b377-386e6ad89f3a","created_time":"2021-11-17T00:09:00.000Z","last_edited_time":"2021-11-20T17:33:00.000Z","has_children":true,"archived":false,"type":"unsupported","unsupported":{}},"02d1aec5-cfab-4124-b89d-d2ca17a733b2":{"object":"block","id":"02d1aec5-cfab-4124-b89d-d2ca17a733b2","created_time":"2021-11-19T04:10:00.000Z","last_edited_time":"2021-11-20T17:33:00.000Z","has_children":false,"archived":false,"type":"paragraph","paragraph":{"text":[]}},"aaa11617-35ff-43a6-a21c-18645efa3437":{"object":"block","id":"aaa11617-35ff-43a6-a21c-18645efa3437","created_time":"2021-11-19T04:10:00.000Z","last_edited_time":"2021-11-20T17:39:00.000Z","has_children":false,"archived":false,"type":"paragraph","paragraph":{"text":[{"type":"text","text":{"content":"Lorem ","link":null},"annotations":{"bold":false,"italic":false,"strikethrough":false,"underline":false,"code":false,"color":"default"},"plain_text":"Lorem ","href":null},{"type":"text","text":{"content":"ipsum","link":null},"annotations":{"bold":false,"italic":false,"strikethrough":false,"underline":false,"code":false,"color":"gray"},"plain_text":"ipsum","href":null},{"type":"text","text":{"content":" ","link":null},"annotations":{"bold":false,"italic":false,"strikethrough":false,"underline":false,"code":false,"color":"default"},"plain_text":" ","href":null},{"type":"text","text":{"content":"dolor","link":null},"annotations":{"bold":false,"italic":false,"strikethrough":false,"underline":false,"code":false,"color":"brown"},"plain_text":"dolor","href":null},{"type":"text","text":{"content":" ","link":null},"annotations":{"bold":false,"italic":false,"strikethrough":false,"underline":false,"code":false,"color":"default"},"plain_text":" ","href":null},{"type":"text","text":{"content":"sit","link":null},"annotations":{"bold":false,"italic":false,"strikethrough":false,"underline":false,"code":false,"color":"orange"},"plain_text":"sit","href":null},{"type":"text","text":{"content":" ","link":null},"annotations":{"bold":false,"italic":false,"strikethrough":false,"underline":false,"code":false,"color":"default"},"plain_text":" ","href":null},{"type":"text","text":{"content":"amet","link":null},"annotations":{"bold":false,"italic":false,"strikethrough":false,"underline":false,"code":false,"color":"yellow"},"plain_text":"amet","href":null},{"type":"text","text":{"content":", ","link":null},"annotations":{"bold":false,"italic":false,"strikethrough":false,"underline":false,"code":false,"color":"default"},"plain_text":", ","href":null},{"type":"text","text":{"content":"consectetuer","link":null},"annotations":{"bold":false,"italic":false,"strikethrough":false,"underline":false,"code":false,"color":"green"},"plain_text":"consectetuer","href":null},{"type":"text","text":{"content":" ","link":null},"annotations":{"bold":false,"italic":false,"strikethrough":false,"underline":false,"code":false,"color":"default"},"plain_text":" ","href":null},{"type":"text","text":{"content":"adipiscing","link":null},"annotations":{"bold":false,"italic":false,"strikethrough":false,"underline":false,"code":false,"color":"blue"},"plain_text":"adipiscing","href":null},{"type":"text","text":{"content":" ","link":null},"annotations":{"bold":false,"italic":false,"strikethrough":false,"underline":false,"code":false,"color":"default"},"plain_text":" ","href":null},{"type":"text","text":{"content":"elit","link":null},"annotations":{"bold":false,"italic":false,"strikethrough":false,"underline":false,"code":false,"color":"purple"},"plain_text":"elit","href":null},{"type":"text","text":{"content":". ","link":null},"annotations":{"bold":false,"italic":false,"strikethrough":false,"underline":false,"code":false,"color":"default"},"plain_text":". ","href":null},{"type":"text","text":{"content":"Aenean","link":null},"annotations":{"bold":false,"italic":false,"strikethrough":false,"underline":false,"code":false,"color":"pink"},"plain_text":"Aenean","href":null},{"type":"text","text":{"content":" ","link":null},"annotations":{"bold":false,"italic":false,"strikethrough":false,"underline":false,"code":false,"color":"default"},"plain_text":" ","href":null},{"type":"text","text":{"content":"commodo","link":null},"annotations":{"bold":false,"italic":false,"strikethrough":false,"underline":false,"code":false,"color":"red"},"plain_text":"commodo","href":null},{"type":"text","text":{"content":" ligula\neget ","link":null},"annotations":{"bold":false,"italic":false,"strikethrough":false,"underline":false,"code":false,"color":"default"},"plain_text":" ligula\neget ","href":null},{"type":"text","text":{"content":"dolor","link":null},"annotations":{"bold":false,"italic":false,"strikethrough":false,"underline":false,"code":false,"color":"gray_background"},"plain_text":"dolor","href":null},{"type":"text","text":{"content":". ","link":null},"annotations":{"bold":false,"italic":false,"strikethrough":false,"underline":false,"code":false,"color":"default"},"plain_text":". ","href":null},{"type":"text","text":{"content":"Aenean","link":null},"annotations":{"bold":false,"italic":false,"strikethrough":false,"underline":false,"code":false,"color":"brown_background"},"plain_text":"Aenean","href":null},{"type":"text","text":{"content":" ","link":null},"annotations":{"bold":false,"italic":false,"strikethrough":false,"underline":false,"code":false,"color":"default"},"plain_text":" ","href":null},{"type":"text","text":{"content":"massa","link":null},"annotations":{"bold":false,"italic":false,"strikethrough":false,"underline":false,"code":false,"color":"orange_background"},"plain_text":"massa","href":null},{"type":"text","text":{"content":". ","link":null},"annotations":{"bold":false,"italic":false,"strikethrough":false,"underline":false,"code":false,"color":"default"},"plain_text":". ","href":null},{"type":"text","text":{"content":"Cum","link":null},"annotations":{"bold":false,"italic":false,"strikethrough":false,"underline":false,"code":false,"color":"yellow_background"},"plain_text":"Cum","href":null},{"type":"text","text":{"content":" ","link":null},"annotations":{"bold":false,"italic":false,"strikethrough":false,"underline":false,"code":false,"color":"default"},"plain_text":" ","href":null},{"type":"text","text":{"content":"sociis","link":null},"annotations":{"bold":false,"italic":false,"strikethrough":false,"underline":false,"code":false,"color":"green_background"},"plain_text":"sociis","href":null},{"type":"text","text":{"content":" ","link":null},"annotations":{"bold":false,"italic":false,"strikethrough":false,"underline":false,"code":false,"color":"default"},"plain_text":" ","href":null},{"type":"text","text":{"content":"natoque","link":null},"annotations":{"bold":false,"italic":false,"strikethrough":false,"underline":false,"code":false,"color":"blue_background"},"plain_text":"natoque","href":null},{"type":"text","text":{"content":" ","link":null},"annotations":{"bold":false,"italic":false,"strikethrough":false,"underline":false,"code":false,"color":"default"},"plain_text":" ","href":null},{"type":"text","text":{"content":"penatibus","link":null},"annotations":{"bold":false,"italic":false,"strikethrough":false,"underline":false,"code":false,"color":"purple_background"},"plain_text":"penatibus","href":null},{"type":"text","text":{"content":" ","link":null},"annotations":{"bold":false,"italic":false,"strikethrough":false,"underline":false,"code":false,"color":"default"},"plain_text":" ","href":null},{"type":"text","text":{"content":"et","link":null},"annotations":{"bold":false,"italic":false,"strikethrough":false,"underline":false,"code":false,"color":"pink_background"},"plain_text":"et","href":null},{"type":"text","text":{"content":" ","link":null},"annotations":{"bold":false,"italic":false,"strikethrough":false,"underline":false,"code":false,"color":"default"},"plain_text":" ","href":null},{"type":"text","text":{"content":"magnis","link":null},"annotations":{"bold":false,"italic":false,"strikethrough":false,"underline":false,"code":false,"color":"red_background"},"plain_text":"magnis","href":null},{"type":"text","text":{"content":" dis parturient\nmontes, ","link":null},"annotations":{"bold":false,"italic":false,"strikethrough":false,"underline":false,"code":false,"color":"default"},"plain_text":" dis parturient\nmontes, ","href":null},{"type":"text","text":{"content":"nascetur","link":null},"annotations":{"bold":false,"italic":false,"strikethrough":false,"underline":false,"code":false,"color":"gray_background"},"plain_text":"nascetur","href":null},{"type":"text","text":{"content":" ridiculus mus. Donec quam felis, ultricies nec, pellentesque\neu, pretium quis, sem. Nulla consequat massa quis enim. Donec pede justo,\nfringilla vel, aliquet nec, vulputate eget, arcu. In enim justo, rhoncus ut,\nimperdiet a, venenatis vitae, justo. Nullam dictum felis eu pede mollis pretium.\nInteger tincidunt. Cras dapibus. Vivamus elementum semper nisi. Aenean vulputate\neleifend tellus. Aenean leo ligula, porttitor eu, consequat vitae, eleifend ac,\nenim. Aliquam lorem ante, dapibus in, viverra quis, feugiat a, tellus. Phasellus\nviverra nulla ut metus varius laoreet. Quisque rutrum. Aenean imperdiet. Etiam\nultricies nisi vel augue. Curabitur ullamcorper ultricies nisi. Nam eget dui.\nLorem ipsum dolor sit amet, consectetuer adipiscing elit. \nAenean commodo ligula\neget dolor. Aenean massa. Cum sociis natoque penatibus et magnis dis parturient\nmontes, nascetur ridiculus mus. Donec quam felis, ultricies nec, pellentesque\neu, pretium quis, sem. Nulla consequat massa quis enim. Donec pede justo,\nfringilla vel, aliquet nec, vulputate eget, arcu. In enim justo, rhoncus ut,\nimperdiet a, venenatis vitae, justo. Nullam dictum felis eu pede mollis pretium.\nInteger tincidunt. Cras dapibus. Vivamus elementum semper nisi. Aenean vulputate\neleifend tellus. Aenean leo ligula, porttitor eu, consequat vitae, eleifend ac,\nenim. Aliquam lorem ante, dapibus in, viverra quis, feugiat a, tellus. Phasellus","link":null},"annotations":{"bold":false,"italic":false,"strikethrough":false,"underline":false,"code":false,"color":"default"},"plain_text":" ridiculus mus. Donec quam felis, ultricies nec, pellentesque\neu, pretium quis, sem. Nulla consequat massa quis enim. Donec pede justo,\nfringilla vel, aliquet nec, vulputate eget, arcu. In enim justo, rhoncus ut,\nimperdiet a, venenatis vitae, justo. Nullam dictum felis eu pede mollis pretium.\nInteger tincidunt. Cras dapibus. Vivamus elementum semper nisi. Aenean vulputate\neleifend tellus. Aenean leo ligula, porttitor eu, consequat vitae, eleifend ac,\nenim. Aliquam lorem ante, dapibus in, viverra quis, feugiat a, tellus. Phasellus\nviverra nulla ut metus varius laoreet. Quisque rutrum. Aenean imperdiet. Etiam\nultricies nisi vel augue. Curabitur ullamcorper ultricies nisi. Nam eget dui.\nLorem ipsum dolor sit amet, consectetuer adipiscing elit. \nAenean commodo ligula\neget dolor. Aenean massa. Cum sociis natoque penatibus et magnis dis parturient\nmontes, nascetur ridiculus mus. Donec quam felis, ultricies nec, pellentesque\neu, pretium quis, sem. Nulla consequat massa quis enim. Donec pede justo,\nfringilla vel, aliquet nec, vulputate eget, arcu. In enim justo, rhoncus ut,\nimperdiet a, venenatis vitae, justo. Nullam dictum felis eu pede mollis pretium.\nInteger tincidunt. Cras dapibus. Vivamus elementum semper nisi. Aenean vulputate\neleifend tellus. Aenean leo ligula, porttitor eu, consequat vitae, eleifend ac,\nenim. Aliquam lorem ante, dapibus in, viverra quis, feugiat a, tellus. Phasellus","href":null}]}},"fdb5355a-5d60-49dc-97bb-06f3e9f2f330":{"object":"block","id":"fdb5355a-5d60-49dc-97bb-06f3e9f2f330","created_time":"2021-11-20T17:33:00.000Z","last_edited_time":"2021-11-20T18:55:00.000Z","has_children":false,"archived":false,"type":"code","code":{"text":[{"type":"text","text":{"content":"function Hello() {\n\tconsole.log('Hello World! 🚀');\n}\n\nHello()\n// Hello World! 🚀","link":null},"annotations":{"bold":false,"italic":false,"strikethrough":false,"underline":false,"code":false,"color":"default"},"plain_text":"function Hello() {\n\tconsole.log('Hello World! 🚀');\n}\n\nHello()\n// Hello World! 🚀","href":null}],"language":"javascript"}},"4d25704e-63b1-4f1b-bfd4-0764186deaaf":{"object":"block","id":"4d25704e-63b1-4f1b-bfd4-0764186deaaf","created_time":"2021-11-20T19:03:00.000Z","last_edited_time":"2021-11-20T19:03:00.000Z","has_children":false,"archived":false,"type":"bulleted_list_item","bulleted_list_item":{"text":[{"type":"text","text":{"content":"Item one","link":null},"annotations":{"bold":false,"italic":false,"strikethrough":false,"underline":false,"code":false,"color":"default"},"plain_text":"Item one","href":null}]}},"47a1b4ba-ee9d-4996-a4c3-cbd11c67f9dd":{"object":"block","id":"47a1b4ba-ee9d-4996-a4c3-cbd11c67f9dd","created_time":"2021-11-20T19:03:00.000Z","last_edited_time":"2021-11-20T19:03:00.000Z","has_children":false,"archived":false,"type":"bulleted_list_item","bulleted_list_item":{"text":[{"type":"text","text":{"content":"Item two","link":null},"annotations":{"bold":false,"italic":false,"strikethrough":false,"underline":false,"code":false,"color":"default"},"plain_text":"Item two","href":null}]}},"a7d39d42-255e-44ab-9054-67af10b642b2":{"object":"block","id":"a7d39d42-255e-44ab-9054-67af10b642b2","created_time":"2021-11-20T19:05:00.000Z","last_edited_time":"2021-11-20T19:05:00.000Z","has_children":false,"archived":false,"type":"numbered_list_item","numbered_list_item":{"text":[{"type":"text","text":{"content":"Item one","link":null},"annotations":{"bold":false,"italic":false,"strikethrough":false,"underline":false,"code":false,"color":"default"},"plain_text":"Item one","href":null}]}},"c818e63b-968d-4d95-b07a-ca1e3c2d24f9":{"object":"block","id":"c818e63b-968d-4d95-b07a-ca1e3c2d24f9","created_time":"2021-11-20T19:05:00.000Z","last_edited_time":"2021-11-20T19:06:00.000Z","has_children":false,"archived":false,"type":"numbered_list_item","numbered_list_item":{"text":[{"type":"text","text":{"content":"Item two","link":null},"annotations":{"bold":false,"italic":false,"strikethrough":false,"underline":false,"code":false,"color":"default"},"plain_text":"Item two","href":null}]}},"fbaa68b5-e786-44f5-8fdd-31b59af6c6ae":{"object":"block","id":"fbaa68b5-e786-44f5-8fdd-31b59af6c6ae","created_time":"2021-11-20T20:51:00.000Z","last_edited_time":"2021-11-20T20:51:00.000Z","has_children":false,"archived":false,"type":"to_do","to_do":{"text":[{"type":"text","text":{"content":"Item one","link":null},"annotations":{"bold":false,"italic":false,"strikethrough":false,"underline":false,"code":false,"color":"default"},"plain_text":"Item one","href":null}],"checked":false}},"3f5db090-7841-4121-8d3f-ed9cecc3c953":{"object":"block","id":"3f5db090-7841-4121-8d3f-ed9cecc3c953","created_time":"2021-11-20T20:51:00.000Z","last_edited_time":"2021-11-20T20:51:00.000Z","has_children":false,"archived":false,"type":"to_do","to_do":{"text":[{"type":"text","text":{"content":"Item two","link":null},"annotations":{"bold":false,"italic":false,"strikethrough":false,"underline":false,"code":false,"color":"default"},"plain_text":"Item two","href":null}],"checked":false}},"1506f17a-6834-4ded-bf6c-746c8f1df30d":{"object":"block","id":"1506f17a-6834-4ded-bf6c-746c8f1df30d","created_time":"2021-11-20T20:51:00.000Z","last_edited_time":"2021-11-20T20:51:00.000Z","has_children":false,"archived":false,"type":"to_do","to_do":{"text":[{"type":"text","text":{"content":"Item one","link":null},"annotations":{"bold":false,"italic":false,"strikethrough":false,"underline":false,"code":false,"color":"default"},"plain_text":"Item one","href":null}],"checked":true}},"2bc46609-ec1e-45fa-a3c0-c77f6f33b306":{"object":"block","id":"2bc46609-ec1e-45fa-a3c0-c77f6f33b306","created_time":"2021-11-20T20:51:00.000Z","last_edited_time":"2021-11-20T20:51:00.000Z","has_children":false,"archived":false,"type":"to_do","to_do":{"text":[{"type":"text","text":{"content":"Item two","link":null},"annotations":{"bold":false,"italic":false,"strikethrough":false,"underline":false,"code":false,"color":"default"},"plain_text":"Item two","href":null}],"checked":true}},"4210a1d4-4cf0-4c24-b820-b4ef8d9f07d3":{"object":"block","id":"4210a1d4-4cf0-4c24-b820-b4ef8d9f07d3","created_time":"2021-11-17T00:09:00.000Z","last_edited_time":"2021-11-17T00:10:00.000Z","has_children":false,"archived":false,"type":"unsupported","unsupported":{}},"70f71ac5-461c-4f81-8cea-f0acaa92ba4f":{"object":"block","id":"70f71ac5-461c-4f81-8cea-f0acaa92ba4f","created_time":"2021-11-17T00:09:00.000Z","last_edited_time":"2021-11-17T00:10:00.000Z","has_children":false,"archived":false,"type":"unsupported","unsupported":{}},"b975fbc2-e07f-4e7b-a1e8-25cb5445a9cc":{"object":"block","id":"b975fbc2-e07f-4e7b-a1e8-25cb5445a9cc","created_time":"2021-11-17T00:09:00.000Z","last_edited_time":"2021-11-17T00:10:00.000Z","has_children":false,"archived":false,"type":"unsupported","unsupported":{}},"6a471c12-26bb-41af-8012-f6e53d9b3e00":{"object":"block","id":"6a471c12-26bb-41af-8012-f6e53d9b3e00","created_time":"2021-11-20T17:33:00.000Z","last_edited_time":"2021-11-20T17:33:00.000Z","has_children":false,"archived":false,"type":"unsupported","unsupported":{}}}